stefaneicher/__init__.py
stefaneicher-0.1.0.dist-info/WHEEL
stefaneicher-0.1.0.dist-info/METADATA
stefaneicher-0.1.0.dist-info/RECORD
