Metadata-Version: 2.1
Name: stefaneicher
Version: 0.1.0
Summary: 
Author: Stefan Eicher
Author-email: stefan.eicher@gmail.com
Requires-Python: >=3.9,<4.0
Classifier: Programming Language :: Python :: 3
Classifier: Programming Language :: Python :: 3.9
Requires-Dist: conan (>=1.36.0,<2.0.0)
